{
    "usuario": "Usuario",
    "fecha": "2025-05-20 12:24:31",
    "datos": [
        {
            "N°": 1,
            "X": 4.5,
            "Y": 0
        },
        {
            "N°": 2,
            "X": 25.5,
            "Y": 20
        },
        {
            "N°": 3,
            "X": 39.0,
            "Y": 20
        },
        {
            "N°": 4,
            "X": 55.5,
            "Y": 0
        },
        {
            "N°": 5,
            "X": 75.0,
            "Y": 0
        },
        {
            "N°": 6,
            "X": 89.5,
            "Y": 33
        },
        {
            "N°": 7,
            "X": 116.0,
            "Y": 33
        },
        {
            "N°": 8,
            "X": 140.5,
            "Y": 0
        }
    ]
}